pydpkg/__init__.py
pydpkg/base.py
pydpkg/dpkg.py
pydpkg/dpkg_inspect.py
pydpkg/dsc.py
pydpkg/exceptions.py
pydpkg-1.9.5.dist-info/METADATA
pydpkg-1.9.5.dist-info/WHEEL
pydpkg-1.9.5.dist-info/entry_points.txt
pydpkg-1.9.5.dist-info/licenses/LICENSE.txt
pydpkg-1.9.5.dist-info/RECORD
