Metadata-Version: 2.4
Name: pydpkg
Version: 1.9.5
Summary: A python library for parsing debian package control headers and version strings
License: Apache-2.0
License-File: LICENSE.txt
Keywords: apt,debian,dpkg,packaging
Author: Nathan J. Mehl
Author-email: pypi@memory.blank.org
Requires-Python: >=3.9.2,<4.0
Classifier: Development Status :: 5 - Production/Stable
Classifier: License :: OSI Approved :: Apache Software License
Classifier: Programming Language :: Python :: 3
Classifier: Programming Language :: Python :: 3.10
Classifier: Programming Language :: Python :: 3.11
Classifier: Programming Language :: Python :: 3.12
Classifier: Programming Language :: Python :: 3.13
Classifier: Programming Language :: Python :: 3.14
Classifier: Programming Language :: Python :: 3.8
Classifier: Programming Language :: Python :: 3.9
Classifier: Programming Language :: Python :: Implementation :: CPython
Classifier: Topic :: System :: Archiving :: Packaging
Requires-Dist: PGPy13 (==0.6.1rc1)
Requires-Dist: arpy (>=2.3.0,<3.0.0)
Requires-Dist: cryptography (>=44.0.1)
Requires-Dist: six (>=1.16.0,<2.0.0)
Requires-Dist: zstandard (>=0.23.0,<0.24.0)
Project-URL: Homepage, https://github.com/memory/python-dpkg
Project-URL: Repository, https://github.com/memory/python-dpkg.git
